{
  "success": true, 
  "message": "Node details found", 
  "result": {
    "id": 884, 
    "url": "https://www.v2ex.com/go/koukaku", 
    "name": "koukaku", 
    "title": "Ghost in the Shell", 
    "header": "\u300a\u653b\u58f3\u673a\u52a8\u961f\u300b\u662f\u7531\u65e5\u672c\u6f2b\u753b\u5bb6\u58eb\u90ce\u6b63\u5b97 1989 \u5e74 4 \u6708 22 \u65e5\u9996\u6b21\u8fde\u8f7d\u4e8e\u8bb2\u8c08\u793e\u9752\u5e74\u6f2b\u753b\u6708\u520a\u300aYoung Magazine\u6d77\u8d3c\u7248\u300b\u7684\u6f2b\u753b\u3002", 
    "footer": "", 
    "avatar": "https://cdn.v2ex.com/navatar/170c/9449/884_large.png?m=1587640721", 
    "topics": 4, 
    "created": 1448949096, 
    "last_modified": 1587640721
  }
}